ispc_texcomp/__init__.py
ispc_texcomp/_ispc_texcomp.abi3.so
ispc_texcomp/py.typed
ispc_texcomp/__init__.pyi
ispc_texcomp.libs/libgcc_s-7393e603.so.1
ispc_texcomp.libs/libstdc++-1b614e01.so.6.0.32
ispc_texcomp-1.0.1.dist-info/RECORD
ispc_texcomp-1.0.1.dist-info/WHEEL
ispc_texcomp-1.0.1.dist-info/METADATA
ispc_texcomp-1.0.1.dist-info/top_level.txt
ispc_texcomp-1.0.1.dist-info/licenses/LICENSE
