Metadata-Version: 2.4
Name: ispc_texcomp
Version: 1.0.1
Summary: Python bindings for ISPCTextureCompressor
Author-email: Rudolf Kolbe <rkolbe96@gmail.com>
License: MIT License
Project-URL: Homepage, https://github.com/K0lb3/ispc_texcomp_py
Project-URL: Bug Tracker, https://github.com/K0lb3/ispc_texcomp_py/issues
Keywords: python,python3,ispc,texture,texture compression,astc,etc
Classifier: License :: OSI Approved :: MIT License
Classifier: Operating System :: OS Independent
Classifier: Intended Audience :: Developers
Classifier: Programming Language :: Python
Classifier: Programming Language :: Python :: 3
Classifier: Programming Language :: Python :: 3.11
Classifier: Programming Language :: Python :: 3.12
Classifier: Programming Language :: Python :: 3.13
Classifier: Topic :: Multimedia :: Graphics
Classifier: Topic :: Software Development :: Libraries :: Python Modules
Requires-Python: >=3.11
License-File: LICENSE
Provides-Extra: tests
Requires-Dist: pytest; extra == "tests"
Requires-Dist: pillow; extra == "tests"
Requires-Dist: imagehash; extra == "tests"
Requires-Dist: texture2ddecoder; extra == "tests"
Dynamic: license-file
